fleb/esq/ESQ.py
fleb/esq/__init__.py
fleb/esq/mode.py
fleb_esq-0.1.2.dist-info/METADATA
fleb_esq-0.1.2.dist-info/WHEEL
fleb_esq-0.1.2.dist-info/entry_points.txt
fleb_esq-0.1.2.dist-info/licenses/LICENSE
fleb_esq-0.1.2.dist-info/RECORD
