Metadata-Version: 2.4
Name: fleb-esq
Version: 0.1.2
Summary: Escape SeQuence Generator: Another ANSI escape-code tool
Keywords: ANSI,VT100,color,terminal
Author: FLEB (a.k.a. SuperFLEB)
License-Expression: MIT-0
License-File: LICENSE
Classifier: Programming Language :: Python :: 3
Classifier: Environment :: Console
Classifier: Operating System :: OS Independent
Project-URL: Homepage, https://github.com/SuperFLEB/esq
Project-URL: Source, https://github.com/SuperFLEB/esq
Project-URL: Issues, https://github.com/SuperFLEB/esq/issues
Project-URL: Author, https://flebsite.com
Requires-Python: >=3.10
